SVGFTW/__init__.py
SVGFTW/core.py
SVGFTW/utilities.py
SVGFTW/models/__init__.py
SVGFTW/models/svgAIGen.py
SVGFTW/models/svgAIVectorGen.py
SVGFTW/models/svgATSM.py
SVGFTW/models/svgAlgoGen.py
SVGFTW/models/svgAnim.py
SVGFTW/models/svgAudioAnim.py
SVGFTW/models/svgBio.py
SVGFTW/models/svgBioPatterns.py
SVGFTW/models/svgClipMask.py
SVGFTW/models/svgCrypto.py
SVGFTW/models/svgDocument.py
SVGFTW/models/svgElements.py
SVGFTW/models/svgExport.py
SVGFTW/models/svgFactory.py
SVGFTW/models/svgFeedback.py
SVGFTW/models/svgFilter.py
SVGFTW/models/svgHolo.py
SVGFTW/models/svgLiveInt.py
SVGFTW/models/svgMorphing.py
SVGFTW/models/svgParsing.py
SVGFTW/models/svgPathOp.py
SVGFTW/models/svgPhysics.py
SVGFTW/models/svgQuantum.py
SVGFTW/models/svgQuantumLayout.py
SVGFTW/models/svgRandomizer.py
SVGFTW/models/svgStyling.py
SVGFTW/models/svgTextEngine.py
SVGFTW/models/svgchain.py
svgftw-0.1.1.dist-info/METADATA
svgftw-0.1.1.dist-info/WHEEL
svgftw-0.1.1.dist-info/entry_points.txt
svgftw-0.1.1.dist-info/top_level.txt
svgftw-0.1.1.dist-info/RECORD
