Metadata-Version: 2.4
Name: svgftw
Version: 0.1.1
Summary: Advanced SVG manipulation with quantum, AI, and bio-algorithm features
Home-page: https://github.com/svgftw/svgftw
Author: SVGFTW Team
Author-email: info@svgftw.org
Project-URL: Bug Tracker, https://github.com/svgftw/svgftw/issues
Project-URL: Documentation, https://svgftw.readthedocs.io/
Classifier: Development Status :: 4 - Beta
Classifier: Intended Audience :: Developers
Classifier: Intended Audience :: Science/Research
Classifier: License :: OSI Approved :: MIT License
Classifier: Operating System :: OS Independent
Classifier: Programming Language :: Python :: 3
Classifier: Programming Language :: Python :: 3.8
Classifier: Programming Language :: Python :: 3.9
Classifier: Programming Language :: Python :: 3.10
Classifier: Topic :: Scientific/Engineering :: Artificial Intelligence
Classifier: Topic :: Scientific/Engineering :: Quantum Computing
Classifier: Topic :: Multimedia :: Graphics :: Graphics Conversion
Requires-Python: >=3.8
Requires-Dist: numpy>=1.20.0
Requires-Dist: lxml>=4.9.0
Requires-Dist: pillow>=9.0.0
Provides-Extra: ai-basic
Requires-Dist: onnxruntime>=1.8.0; extra == "ai-basic"
Provides-Extra: ai-full
Requires-Dist: onnxruntime>=1.8.0; extra == "ai-full"
Requires-Dist: torch>=1.9.0; extra == "ai-full"
Provides-Extra: ai-cuda
Requires-Dist: onnxruntime>=1.8.0; extra == "ai-cuda"
Requires-Dist: torch>=1.9.0; extra == "ai-cuda"
Requires-Dist: numba>=0.55.0; extra == "ai-cuda"
Provides-Extra: quantum
Requires-Dist: qiskit>=0.34.2; extra == "quantum"
Provides-Extra: bio
Requires-Dist: scikit-bio>=0.5.7; extra == "bio"
Provides-Extra: minimal
Requires-Dist: onnxruntime>=1.8.0; extra == "minimal"
Provides-Extra: recommended
Requires-Dist: onnxruntime>=1.8.0; extra == "recommended"
Requires-Dist: torch>=1.9.0; extra == "recommended"
Requires-Dist: qiskit>=0.34.2; extra == "recommended"
Provides-Extra: complete
Requires-Dist: onnxruntime>=1.8.0; extra == "complete"
Requires-Dist: torch>=1.9.0; extra == "complete"
Requires-Dist: qiskit>=0.34.2; extra == "complete"
Requires-Dist: scikit-bio>=0.5.7; extra == "complete"
Requires-Dist: numba>=0.55.0; extra == "complete"
Provides-Extra: dev
Requires-Dist: pytest>=7.0.0; extra == "dev"
Requires-Dist: pytest-cov>=3.0.0; extra == "dev"
Requires-Dist: black>=22.3.0; extra == "dev"
Requires-Dist: mypy>=0.950; extra == "dev"
Dynamic: author
Dynamic: author-email
Dynamic: classifier
Dynamic: description
Dynamic: description-content-type
Dynamic: home-page
Dynamic: project-url
Dynamic: provides-extra
Dynamic: requires-dist
Dynamic: requires-python
Dynamic: summary
